setup.py
shinkenplugins/__init__.py
shinkenplugins.plugins.snow_clearance.egg-info/PKG-INFO
shinkenplugins.plugins.snow_clearance.egg-info/SOURCES.txt
shinkenplugins.plugins.snow_clearance.egg-info/dependency_links.txt
shinkenplugins.plugins.snow_clearance.egg-info/entry_points.txt
shinkenplugins.plugins.snow_clearance.egg-info/namespace_packages.txt
shinkenplugins.plugins.snow_clearance.egg-info/requires.txt
shinkenplugins.plugins.snow_clearance.egg-info/top_level.txt
shinkenplugins/plugins/__init__.py
shinkenplugins/plugins/snow_clearance/__init__.py
shinkenplugins/plugins/snow_clearance/snow_clearance.py