Metadata-Version: 1.0
Name: shinkenplugins.plugins.snow-clearance
Version: 1.2
Summary: Check Snow Clearance
Home-page: https://github.com/savoirfairelinux/sfl-shinken-plugins
Author: Grégory Starck
Author-email: gregory.starck@savoirfairelinux.com
License: GPL3+
Platform: any
